custom_accounts_django/__init__.py
custom_accounts_django/admin.py
custom_accounts_django/apps.py
custom_accounts_django/models.py
custom_accounts_django/tests.py
custom_accounts_django/urls.py
custom_accounts_django/views.py
custom_accounts_django/migrations/__init__.py
custom_accounts_django/templates/accounts_index.html
custom_accounts_django/templates/login.html
custom_accounts_django/templates/register.html
Custom_Accounts_Django-0.1.1560515473.dist-info/METADATA
Custom_Accounts_Django-0.1.1560515473.dist-info/WHEEL
Custom_Accounts_Django-0.1.1560515473.dist-info/top_level.txt
Custom_Accounts_Django-0.1.1560515473.dist-info/RECORD
