Metadata-Version: 2.1
Name: Custom-Accounts-Django
Version: 0.1.1560515473
Summary: Cusstomizable Account app for Django
Home-page: https://github.com/JulianKimmig/django_accounts
Author: Julian Kimmig
Author-email: julian-kimmig@gmx.net
License: UNKNOWN
Platform: UNKNOWN
Classifier: Programming Language :: Python :: 3
Classifier: License :: OSI Approved :: MIT License
Classifier: Operating System :: OS Independent
